Workbook

Sheet Guide
A1: Cash-Flow Tracker | Suivi de trésorerie (GNF / USD)
A3: How to use / Mode d'emploi
A4: 1. Settings: enter business name, year, display currency (GNF or USD), exchange rate and opening cash.
A5: Paramètres : nom, année, devise d'affichage, taux de change et trésorerie d'ouverture.
A6: 2. Transactions: one row per income or expense. Pick Type, Category and Currency from the drop-downs.
A7: Transactions : une ligne par encaissement ou décaissement. Choisissez dans les listes déroulantes.
A8: 3. Dashboard: updates automatically (monthly cash flow, closing cash, runway, expenses by category).
A9: Tableau de bord : se met à jour automatiquement.
A11: Colour code
A12: Blue text = cells you type in. Yellow fill = key settings to update. Black = formulas (do not edit).
A14: Important assumptions
A15: • One exchange rate (GNF per 1 USD) converts all USD entries. The rate in Settings is a PLACEHOLDER: replace it with your current rate.
... A18: • The Transactions sheet is ready for 500 entries (rows 5–504).

Sheet Settings
A1: Settings | Paramètres
D2: Categories / Catégories | E2: Type
A3: Business name / Nom de l'entreprise | B3: My Business
A4: Year / Année | B4: 2026 | D4: Sales / Ventes | E4: Income
A5: Display currency / Devise d'affichage | B5: GNF | D5: Services | E5: Income
A6: Exchange rate (GNF per 1 USD) / Taux de change | B6: 8650 | D6: Other income / Autres revenus | E6: Income
A7: Opening cash GNF / Trésorerie d'ouverture (GNF) | B7: 5000000 | D7: Loan received / Prêt reçu | E7: Income
A8: Opening cash USD / Trésorerie d'ouverture (USD) | B8: 200 | D8: Capital injection / Apport | E8: Income
A9: Display factor (GNF → display currency) | B9: =IF(B5="USD",1/B6,1) -> 1 | D9: Rent / Loyer | E9: Expense
A10: Exchange rate and opening balances are example values entered by the author; replace them. | D10: Salaries / Salaires | E10: Expense
D11: Transport | E11: Expense
D12: Electricity & Water / EDG & SEG | E12: Expense
D13: Stock & Supplies / Stock | E13: Expense
D14: Marketing | E14: Expense
D15: Taxes & Fees / Impôts | E15: Expense
D16: Loan repayment / Remb. prêt | E16: Expense
D17: Owner withdrawals / Prélèvements | E17: Expense
D18: Other expense / Autres charges | E18: Expense

Sheet Transactions
A1: Transactions | Opérations
A2: Type in blue columns A–F. Columns G–I calculate automatically. / Saisissez les colonnes A–F.
A4: Date | B4: Description | C4: Type | D4: Category / Catégorie | E4: Currency / Devise | F4: Amount / Montant | G4: Amount GNF | H4: Amount USD | I4: Month
A5: 46027 | B5: (Example) Cash sales week 1 | C5: Income | D5: Sales / Ventes | E5: GNF | F5: 12000000 | G5: =IF(OR(A5="",F5=""),"",IF(E5="USD",F5*Settings!$B$6,F5)) -> 12000000 | H5: =IF(OR(A5="",F5=""),"",IF(E5="USD",F5,F5/Settings!$B$6)) -> 1387.2832 | I5: =IF(A5="","",DATE(YEAR(A5),MONTH(A5),1)) -> 46023
A6: 46032 | B6: (Example) Shop rent | C6: Expense | D6: Rent / Loyer | E6: GNF | F6: 3000000 | G6: =IF(OR(A6="",F6=""),"",IF(E6="USD",F6*Settings!$B$6,F6)) -> 3000000 | H6: =IF(OR(A6="",F6=""),"",IF(E6="USD",F6,F6/Settings!$B$6)) -> 346.82081 | I6: =IF(A6="","",DATE(YEAR(A6),MONTH(A6),1)) -> 46023
A7: 46037 | B7: (Example) Consulting invoice | C7: Income | D7: Services | E7: USD | F7: 450 | G7: =IF(OR(A7="",F7=""),"",IF(E7="USD",F7*Settings!$B$6,F7)) -> 3892500 | H7: =IF(OR(A7="",F7=""),"",IF(E7="USD",F7,F7/Settings!$B$6)) -> 450 | I7: =IF(A7="","",DATE(YEAR(A7),MONTH(A7),1)) -> 46023
A8: 46050 | B8: (Example) Salaries | C8: Expense | D8: Salaries / Salaires | E8: GNF | F8: 4500000 | G8: =IF(OR(A8="",F8=""),"",IF(E8="USD",F8*Settings!$B$6,F8)) -> 4500000 | H8: =IF(OR(A8="",F8=""),"",IF(E8="USD",F8,F8/Settings!$B$6)) -> 520.23121 | I8: =IF(A8="","",DATE(YEAR(A8),MONTH(A8),1)) -> 46023
A9: 46059 | B9: (Example) Cash sales | C9: Income | D9: Sales / Ventes | E9: GNF | F9: 14500000 | G9: =IF(OR(A9="",F9=""),"",IF(E9="USD",F9*Settings!$B$6,F9)) -> 14500000 | H9: =IF(OR(A9="",F9=""),"",IF(E9="USD",F9,F9/Settings!$B$6)) -> 1676.3006 | I9: =IF(A9="","",DATE(YEAR(A9),MONTH(A9),1)) -> 46054
A10: 46065 | B10: (Example) Imported stock | C10: Expense | D10: Stock & Supplies / Stock | E10: USD | F10: 600 | G10: =IF(OR(A10="",F10=""),"",IF(E10="USD",F10*Settings!$B$6,F10)) -> 5190000 | H10: =IF(OR(A10="",F10=""),"",IF(E10="USD",F10,F10/Settings!$B$6)) -> 600 | I10: =IF(A10="","",DATE(YEAR(A10),MONTH(A10),1)) -> 46054
A11: 46073 | B11: (Example) Electricity & water | C11: Expense | D11: Electricity & Water / EDG & SEG | E11: GNF | F11: 650000 | G11: =IF(OR(A11="",F11=""),"",IF(E11="USD",F11*Settings!$B$6,F11)) -> 650000 | H11: =IF(OR(A11="",F11=""),"",IF(E11="USD",F11,F11/Settings!$B$6)) -> 75.144509 | I11: =IF(A11="","",DATE(YEAR(A11),MONTH(A11),1)) -> 46054
A12: 46085 | B12: (Example) Cash sales | C12: Income | D12: Sales / Ventes | E12: GNF | F12: 16000000 | G12: =IF(OR(A12="",F12=""),"",IF(E12="USD",F12*Settings!$B$6,F12)) -> 16000000 | H12: =IF(OR(A12="",F12=""),"",IF(E12="USD",F12,F12/Settings!$B$6)) -> 1849.711 | I12: =IF(A12="","",DATE(YEAR(A12),MONTH(A12),1)) -> 46082
A13: 46099 | B13: (Example) Facebook ads | C13: Expense | D13: Marketing | E13: GNF | F13: 800000 | G13: =IF(OR(A13="",F13=""),"",IF(E13="USD",F13*Settings!$B$6,F13)) -> 800000 | H13: =IF(OR(A13="",F13=""),"",IF(E13="USD",F13,F13/Settings!$B$6)) -> 92.485549 | I13: =IF(A13="","",DATE(YEAR(A13),MONTH(A13),1)) -> 46082
A14: 46106 | B14: (Example) Taxes | C14: Expense | D14: Taxes & Fees / Impôts | E14: GNF | F14: 1200000 | G14: =IF(OR(A14="",F14=""),"",IF(E14="USD",F14*Settings!$B$6,F14)) -> 1200000 | H14: =IF(OR(A14="",F14=""),"",IF(E14="USD",F14,F14/Settings!$B$6)) -> 138.72832 | I14: =IF(A14="","",DATE(YEAR(A14),MONTH(A14),1)) -> 46082
A15: 46115 | B15: (Example) Services invoice | C15: Income | D15: Services | E15: USD | F15: 900 | G15: =IF(OR(A15="",F15=""),"",IF(E15="USD",F15*Settings!$B$6,F15)) -> 7785000 | H15: =IF(OR(A15="",F15=""),"",IF(E15="USD",F15,F15/Settings!$B$6)) -> 900 | I15: =IF(A15="","",DATE(YEAR(A15),MONTH(A15),1)) -> 46113
A16: 46127 | B16: (Example) Transport | C16: Expense | D16: Transport | E16: GNF | F16: 450000 | G16: =IF(OR(A16="",F16=""),"",IF(E16="USD",F16*Settings!$B$6,F16)) -> 450000 | H16: =IF(OR(A16="",F16=""),"",IF(E16="USD",F16,F16/Settings!$B$6)) -> 52.023121 | I16: =IF(A16="","",DATE(YEAR(A16),MONTH(A16),1)) -> 46113
G17: =IF(OR(A17="",F17=""),"",IF(E17="USD",F17*Settings!$B$6,F17)) | H17: =IF(OR(A17="",F17=""),"",IF(E17="USD",F17,F17/Settings!$B$6)) | I17: =IF(A17="","",DATE(YEAR(A17),MONTH(A17),1))
G18: =IF(OR(A18="",F18=""),"",IF(E18="USD",F18*Settings!$B$6,F18)) | H18: =IF(OR(A18="",F18=""),"",IF(E18="USD",F18,F18/Settings!$B$6)) | I18: =IF(A18="","",DATE(YEAR(A18),MONTH(A18),1))
G19: =IF(OR(A19="",F19=""),"",IF(E19="USD",F19*Settings!$B$6,F19)) | H19: =IF(OR(A19="",F19=""),"",IF(E19="USD",F19,F19/Settings!$B$6)) | I19: =IF(A19="","",DATE(YEAR(A19),MONTH(A19),1))
G20: =IF(OR(A20="",F20=""),"",IF(E20="USD",F20*Settings!$B$6,F20)) | H20: =IF(OR(A20="",F20=""),"",IF(E20="USD",F20,F20/Settings!$B$6)) | I20: =IF(A20="","",DATE(YEAR(A20),MONTH(A20),1))
G21: =IF(OR(A21="",F21=""),"",IF(E21="USD",F21*Settings!$B$6,F21)) | H21: =IF(OR(A21="",F21=""),"",IF(E21="USD",F21,F21/Settings!$B$6)) | I21: =IF(A21="","",DATE(YEAR(A21),MONTH(A21),1))
G22: =IF(OR(A22="",F22=""),"",IF(E22="USD",F22*Settings!$B$6,F22)) | H22: =IF(OR(A22="",F22=""),"",IF(E22="USD",F22,F22/Settings!$B$6)) | I22: =IF(A22="","",DATE(YEAR(A22),MONTH(A22),1))
G23: =IF(OR(A23="",F23=""),"",IF(E23="USD",F23*Settings!$B$6,F23)) | H23: =IF(OR(A23="",F23=""),"",IF(E23="USD",F23,F23/Settings!$B$6)) | I23: =IF(A23="","",DATE(YEAR(A23),MONTH(A23),1))
G24: =IF(OR(A24="",F24=""),"",IF(E24="USD",F24*Settings!$B$6,F24)) | H24: =IF(OR(A24="",F24=""),"",IF(E24="USD",F24,F24/Settings!$B$6)) | I24: =IF(A24="","",DATE(YEAR(A24),MONTH(A24),1))
G25: =IF(OR(A25="",F25=""),"",IF(E25="USD",F25*Settings!$B$6,F25)) | H25: =IF(OR(A25="",F25=""),"",IF(E25="USD",F25,F25/Settings!$B$6)) | I25: =IF(A25="","",DATE(YEAR(A25),MONTH(A25),1))
G26: =IF(OR(A26="",F26=""),"",IF(E26="USD",F26*Settings!$B$6,F26)) | H26: =IF(OR(A26="",F26=""),"",IF(E26="USD",F26,F26/Settings!$B$6)) | I26: =IF(A26="","",DATE(YEAR(A26),MONTH(A26),1))
G27: =IF(OR(A27="",F27=""),"",IF(E27="USD",F27*Settings!$B$6,F27)) | H27: =IF(OR(A27="",F27=""),"",IF(E27="USD",F27,F27/Settings!$B$6)) | I27: =IF(A27="","",DATE(YEAR(A27),MONTH(A27),1))
G28: =IF(OR(A28="",F28=""),"",IF(E28="USD",F28*Settings!$B$6,F28)) | H28: =IF(OR(A28="",F28=""),"",IF(E28="USD",F28,F28/Settings!$B$6)) | I28: =IF(A28="","",DATE(YEAR(A28),MONTH(A28),1))
... G504: =IF(OR(A504="",F504=""),"",IF(E504="USD",F504*Settings!$B$6,F504)) | H504: =IF(OR(A504="",F504=""),"",IF(E504="USD",F504,F504/Settings!$B$6)) | I504: =IF(A504="","",DATE(YEAR(A504),MONTH(A504),1))

Sheet Dashboard
A1: Dashboard | Tableau de bord
A2: =Settings!B3&" | "&Settings!B4&" | Amounts in "&Settings!B5 -> My Business | 2026 | Amounts in GNF
A4: Opening cash / Trésorerie d'ouverture | B4: =(Settings!B7+Settings!B8*Settings!B6)*Settings!B9 -> 6730000
A5: Total income / Total encaissements | B5: =SUM(B15:B26) -> 54177500
A6: Total expenses / Total décaissements | B6: =SUM(C15:C26) -> 15790000
A7: Net cash flow / Flux net | B7: =B5-B6 -> 38387500
A8: Closing cash / Trésorerie de clôture | B8: =E26 -> 45117500
A9: Avg monthly expenses / Dépenses mensuelles moy. | B9: =IF(COUNTIF(C15:C26,">0")=0,0,B6/COUNTIF(C15:C26,">0")) -> 3947500
A10: Cash runway (months) / Autonomie (mois) | B10: =IF(B9=0,"n/a",B8/B9) -> 11.429386
A13: Monthly cash flow / Flux mensuel | G13: Expenses by category / Dépenses par catégorie
A14: Month / Mois | B14: Income | C14: Expenses | D14: Net | E14: Closing cash | G14: Category | H14: Amount | I14: % of total
A15: =DATE(Settings!$B$4,1,1) -> 46023 | B15: =SUMIFS(Transactions!$G$5:$G$504,Transactions!$I$5:$I$504,$A15,Transactions!$C$5:$C$504,"Income")*Settings!$B$9 -> 15892500 | C15: =SUMIFS(Transactions!$G$5:$G$504,Transactions!$I$5:$I$504,$A15,Transactions!$C$5:$C$504,"Expense")*Settings!$B$9 -> 7500000 | D15: =B15-C15 -> 8392500 | E15: =$B$4+D15 -> 15122500 | G15: =Settings!D9 -> Rent / Loyer | H15: =SUMIFS(Transactions!$G$5:$G$504,Transactions!$C$5:$C$504,"Expense",Transactions!$D$5:$D$504,G15,Transactions!$A$5:$A$504,">="&DATE(Settings!$B$4,1,1),Transactions!$A$5:$A$504,"<="&DATE(Settings!$B$4,12,31))*Settings!$B$9 -> 3000000 | I15: =IF($H$25=0,0,H15/$H$25) -> 0.18999367
A16: =DATE(Settings!$B$4,2,1) -> 46054 | B16: =SUMIFS(Transactions!$G$5:$G$504,Transactions!$I$5:$I$504,$A16,Transactions!$C$5:$C$504,"Income")*Settings!$B$9 -> 14500000 | C16: =SUMIFS(Transactions!$G$5:$G$504,Transactions!$I$5:$I$504,$A16,Transactions!$C$5:$C$504,"Expense")*Settings!$B$9 -> 5840000 | D16: =B16-C16 -> 8660000 | E16: =E15+D16 -> 23782500 | G16: =Settings!D10 -> Salaries / Salaires | H16: =SUMIFS(Transactions!$G$5:$G$504,Transactions!$C$5:$C$504,"Expense",Transactions!$D$5:$D$504,G16,Transactions!$A$5:$A$504,">="&DATE(Settings!$B$4,1,1),Transactions!$A$5:$A$504,"<="&DATE(Settings!$B$4,12,31))*Settings!$B$9 -> 4500000 | I16: =IF($H$25=0,0,H16/$H$25) -> 0.2849905
A17: =DATE(Settings!$B$4,3,1) -> 46082 | B17: =SUMIFS(Transactions!$G$5:$G$504,Transactions!$I$5:$I$504,$A17,Transactions!$C$5:$C$504,"Income")*Settings!$B$9 -> 16000000 | C17: =SUMIFS(Transactions!$G$5:$G$504,Transactions!$I$5:$I$504,$A17,Transactions!$C$5:$C$504,"Expense")*Settings!$B$9 -> 2000000 | D17: =B17-C17 -> 14000000 | E17: =E16+D17 -> 37782500 | G17: =Settings!D11 -> Transport | H17: =SUMIFS(Transactions!$G$5:$G$504,Transactions!$C$5:$C$504,"Expense",Transactions!$D$5:$D$504,G17,Transactions!$A$5:$A$504,">="&DATE(Settings!$B$4,1,1),Transactions!$A$5:$A$504,"<="&DATE(Settings!$B$4,12,31))*Settings!$B$9 -> 450000 | I17: =IF($H$25=0,0,H17/$H$25) -> 0.02849905
A18: =DATE(Settings!$B$4,4,1) -> 46113 | B18: =SUMIFS(Transactions!$G$5:$G$504,Transactions!$I$5:$I$504,$A18,Transactions!$C$5:$C$504,"Income")*Settings!$B$9 -> 7785000 | C18: =SUMIFS(Transactions!$G$5:$G$504,Transactions!$I$5:$I$504,$A18,Transactions!$C$5:$C$504,"Expense")*Settings!$B$9 -> 450000 | D18: =B18-C18 -> 7335000 | E18: =E17+D18 -> 45117500 | G18: =Settings!D12 -> Electricity & Water / EDG & SEG | H18: =SUMIFS(Transactions!$G$5:$G$504,Transactions!$C$5:$C$504,"Expense",Transactions!$D$5:$D$504,G18,Transactions!$A$5:$A$504,">="&DATE(Settings!$B$4,1,1),Transactions!$A$5:$A$504,"<="&DATE(Settings!$B$4,12,31))*Settings!$B$9 -> 650000 | I18: =IF($H$25=0,0,H18/$H$25) -> 0.041165294
A19: =DATE(Settings!$B$4,5,1) -> 46143 | B19: =SUMIFS(Transactions!$G$5:$G$504,Transactions!$I$5:$I$504,$A19,Transactions!$C$5:$C$504,"Income")*Settings!$B$9 -> 0 | C19: =SUMIFS(Transactions!$G$5:$G$504,Transactions!$I$5:$I$504,$A19,Transactions!$C$5:$C$504,"Expense")*Settings!$B$9 -> 0 | D19: =B19-C19 -> 0 | E19: =E18+D19 -> 45117500 | G19: =Settings!D13 -> Stock & Supplies / Stock | H19: =SUMIFS(Transactions!$G$5:$G$504,Transactions!$C$5:$C$504,"Expense",Transactions!$D$5:$D$504,G19,Transactions!$A$5:$A$504,">="&DATE(Settings!$B$4,1,1),Transactions!$A$5:$A$504,"<="&DATE(Settings!$B$4,12,31))*Settings!$B$9 -> 5190000 | I19: =IF($H$25=0,0,H19/$H$25) -> 0.32868904
A20: =DATE(Settings!$B$4,6,1) -> 46174 | B20: =SUMIFS(Transactions!$G$5:$G$504,Transactions!$I$5:$I$504,$A20,Transactions!$C$5:$C$504,"Income")*Settings!$B$9 -> 0 | C20: =SUMIFS(Transactions!$G$5:$G$504,Transactions!$I$5:$I$504,$A20,Transactions!$C$5:$C$504,"Expense")*Settings!$B$9 -> 0 | D20: =B20-C20 -> 0 | E20: =E19+D20 -> 45117500 | G20: =Settings!D14 -> Marketing | H20: =SUMIFS(Transactions!$G$5:$G$504,Transactions!$C$5:$C$504,"Expense",Transactions!$D$5:$D$504,G20,Transactions!$A$5:$A$504,">="&DATE(Settings!$B$4,1,1),Transactions!$A$5:$A$504,"<="&DATE(Settings!$B$4,12,31))*Settings!$B$9 -> 800000 | I20: =IF($H$25=0,0,H20/$H$25) -> 0.050664978
A21: =DATE(Settings!$B$4,7,1) -> 46204 | B21: =SUMIFS(Transactions!$G$5:$G$504,Transactions!$I$5:$I$504,$A21,Transactions!$C$5:$C$504,"Income")*Settings!$B$9 -> 0 | C21: =SUMIFS(Transactions!$G$5:$G$504,Transactions!$I$5:$I$504,$A21,Transactions!$C$5:$C$504,"Expense")*Settings!$B$9 -> 0 | D21: =B21-C21 -> 0 | E21: =E20+D21 -> 45117500 | G21: =Settings!D15 -> Taxes & Fees / Impôts | H21: =SUMIFS(Transactions!$G$5:$G$504,Transactions!$C$5:$C$504,"Expense",Transactions!$D$5:$D$504,G21,Transactions!$A$5:$A$504,">="&DATE(Settings!$B$4,1,1),Transactions!$A$5:$A$504,"<="&DATE(Settings!$B$4,12,31))*Settings!$B$9 -> 1200000 | I21: =IF($H$25=0,0,H21/$H$25) -> 0.075997467
A22: =DATE(Settings!$B$4,8,1) -> 46235 | B22: =SUMIFS(Transactions!$G$5:$G$504,Transactions!$I$5:$I$504,$A22,Transactions!$C$5:$C$504,"Income")*Settings!$B$9 -> 0 | C22: =SUMIFS(Transactions!$G$5:$G$504,Transactions!$I$5:$I$504,$A22,Transactions!$C$5:$C$504,"Expense")*Settings!$B$9 -> 0 | D22: =B22-C22 -> 0 | E22: =E21+D22 -> 45117500 | G22: =Settings!D16 -> Loan repayment / Remb. prêt | H22: =SUMIFS(Transactions!$G$5:$G$504,Transactions!$C$5:$C$504,"Expense",Transactions!$D$5:$D$504,G22,Transactions!$A$5:$A$504,">="&DATE(Settings!$B$4,1,1),Transactions!$A$5:$A$504,"<="&DATE(Settings!$B$4,12,31))*Settings!$B$9 -> 0 | I22: =IF($H$25=0,0,H22/$H$25) -> 0
A23: =DATE(Settings!$B$4,9,1) -> 46266 | B23: =SUMIFS(Transactions!$G$5:$G$504,Transactions!$I$5:$I$504,$A23,Transactions!$C$5:$C$504,"Income")*Settings!$B$9 -> 0 | C23: =SUMIFS(Transactions!$G$5:$G$504,Transactions!$I$5:$I$504,$A23,Transactions!$C$5:$C$504,"Expense")*Settings!$B$9 -> 0 | D23: =B23-C23 -> 0 | E23: =E22+D23 -> 45117500 | G23: =Settings!D17 -> Owner withdrawals / Prélèvements | H23: =SUMIFS(Transactions!$G$5:$G$504,Transactions!$C$5:$C$504,"Expense",Transactions!$D$5:$D$504,G23,Transactions!$A$5:$A$504,">="&DATE(Settings!$B$4,1,1),Transactions!$A$5:$A$504,"<="&DATE(Settings!$B$4,12,31))*Settings!$B$9 -> 0 | I23: =IF($H$25=0,0,H23/$H$25) -> 0
A24: =DATE(Settings!$B$4,10,1) -> 46296 | B24: =SUMIFS(Transactions!$G$5:$G$504,Transactions!$I$5:$I$504,$A24,Transactions!$C$5:$C$504,"Income")*Settings!$B$9 -> 0 | C24: =SUMIFS(Transactions!$G$5:$G$504,Transactions!$I$5:$I$504,$A24,Transactions!$C$5:$C$504,"Expense")*Settings!$B$9 -> 0 | D24: =B24-C24 -> 0 | E24: =E23+D24 -> 45117500 | G24: =Settings!D18 -> Other expense / Autres charges | H24: =SUMIFS(Transactions!$G$5:$G$504,Transactions!$C$5:$C$504,"Expense",Transactions!$D$5:$D$504,G24,Transactions!$A$5:$A$504,">="&DATE(Settings!$B$4,1,1),Transactions!$A$5:$A$504,"<="&DATE(Settings!$B$4,12,31))*Settings!$B$9 -> 0 | I24: =IF($H$25=0,0,H24/$H$25) -> 0
A25: =DATE(Settings!$B$4,11,1) -> 46327 | B25: =SUMIFS(Transactions!$G$5:$G$504,Transactions!$I$5:$I$504,$A25,Transactions!$C$5:$C$504,"Income")*Settings!$B$9 -> 0 | C25: =SUMIFS(Transactions!$G$5:$G$504,Transactions!$I$5:$I$504,$A25,Transactions!$C$5:$C$504,"Expense")*Settings!$B$9 -> 0 | D25: =B25-C25 -> 0 | E25: =E24+D25 -> 45117500 | G25: Total | H25: =SUM(H15:H24) -> 15790000 | I25: =SUM(I15:I24) -> 1
A26: =DATE(Settings!$B$4,12,1) -> 46357 | B26: =SUMIFS(Transactions!$G$5:$G$504,Transactions!$I$5:$I$504,$A26,Transactions!$C$5:$C$504,"Income")*Settings!$B$9 -> 0 | C26: =SUMIFS(Transactions!$G$5:$G$504,Transactions!$I$5:$I$504,$A26,Transactions!$C$5:$C$504,"Expense")*Settings!$B$9 -> 0 | D26: =B26-C26 -> 0 | E26: =E25+D26 -> 45117500
A27: Total | B27: =SUM(B15:B26) -> 54177500 | C27: =SUM(C15:C26) -> 15790000 | D27: =SUM(D15:D26) -> 38387500
A28: Opening cash is the balance on 1 Jan of the selected year (see Settings).
